{"Dices House Rules":{"Dices House Rules":{"internalLink":{"count":3,"lastUpdated":1743579290345}}},"Forgotten":{"Forgotten":{"currentFile":{"count":2,"lastUpdated":1743578335837}}},"Rogue":{"Rogue":{"internalLink":{"count":2,"lastUpdated":1745331205909}}},"Shaperite - The Agent":{"Shaperite - The Agent":{"internalLink":{"count":6,"lastUpdated":1745596891117}}},"03-races":{"03-races":{"internalLink":{"count":1,"lastUpdated":1743577079935}}},"classes":{"classes":{"internalLink":{"count":1,"lastUpdated":1743577088754}}},"Ability Scores, Feats & Skills Progression":{"Ability Scores, Feats & Skills Progression":{"internalLink":{"count":1,"lastUpdated":1743577381363}}},"ability-scores-and-modifiers":{"ability-scores-and-modifiers":{"internalLink":{"count":1,"lastUpdated":1743577427114}}},"skills":{"skills":{"internalLink":{"count":1,"lastUpdated":1743577653961}}},"Spells & Levels Tiers":{"Spells & Levels Tiers":{"internalLink":{"count":1,"lastUpdated":1743579240316}}},"Houses Items":{"Houses Items":{"internalLink":{"count":1,"lastUpdated":1743580536785}}},"00.Introduction":{"00.Introduction":{"currentFile":{"count":1,"lastUpdated":1743586723026}}},"Armor Class":{"Armor Class":{"internalLink":{"count":1,"lastUpdated":1743648489861}}},"Black Dragon":{"black-dragon":{"internalLink":{"count":1,"lastUpdated":1743672810557}}},"z_Assets/Misc/MapPlaceholder.png":{"z_Assets/Misc/MapPlaceholder.png":{"internalLink":{"count":1,"lastUpdated":1744789559038}}},"Chromatheus":{"Chromatheus":{"internalLink":{"count":2,"lastUpdated":1745597005937}}},"monk":{"monk":{"internalLink":{"count":3,"lastUpdated":1745332082952}}},"wizard":{"wizard":{"internalLink":{"count":2,"lastUpdated":1745332109116}}},"rogue":{"rogue":{"internalLink":{"count":1,"lastUpdated":1745331214133}}},"bard":{"bard":{"internalLink":{"count":1,"lastUpdated":1745331445799}}},"fighter":{"fighter":{"internalLink":{"count":1,"lastUpdated":1745331588510}}},"warlock":{"warlock":{"internalLink":{"count":1,"lastUpdated":1745331802022}}},"grung-mpmm":{"grung-mpmm":{"internalLink":{"count":1,"lastUpdated":1745332064324}}},"GomuGomuNo":{"GomuGomuNo":{"internalLink":{"count":1,"lastUpdated":1745332077182}}},"goliath-mpmm":{"goliath-mpmm":{"internalLink":{"count":2,"lastUpdated":1745644880169}}},"Jeno":{"Jeno":{"internalLink":{"count":3,"lastUpdated":1745596904882}}},"tabaxi-mpmm":{"tabaxi-mpmm":{"internalLink":{"count":1,"lastUpdated":1745332121419}}},"Kairos":{"Kairos":{"internalLink":{"count":2,"lastUpdated":1745596661772}}},"rogue-soulknife-tce":{"rogue-soulknife-tce":{"internalLink":{"count":1,"lastUpdated":1745332155747}}},"astral-elf-aag":{"astral-elf-aag":{"internalLink":{"count":1,"lastUpdated":1745332164725}}},"Verdian Suyanti":{"Verdian Suyanti":{"internalLink":{"count":1,"lastUpdated":1745332175222}}},"bard-college-of-glamour-xge":{"bard-college-of-glamour-xge":{"internalLink":{"count":1,"lastUpdated":1745332191209}}},"half-elf":{"half-elf":{"internalLink":{"count":1,"lastUpdated":1745332207566}}},"Alizar Valts":{"Alizar Valts":{"internalLink":{"count":2,"lastUpdated":1745597170676}}},"fighter-battle-master":{"fighter-battle-master":{"internalLink":{"count":1,"lastUpdated":1745332287230}}},"elf-high":{"elf-high":{"internalLink":{"count":1,"lastUpdated":1745332308185}}},"Ashenka Roïs":{"Ashenka Roïs":{"internalLink":{"count":2,"lastUpdated":1745597257554}}},"monk-way-of-the-long-death-scag":{"monk-way-of-the-long-death-scag":{"internalLink":{"count":1,"lastUpdated":1745332341454}}},"shadar-kai-mpmm":{"shadar-kai-mpmm":{"internalLink":{"count":1,"lastUpdated":1745332354027}}},"Gwyn":{"Gwyn":{"internalLink":{"count":2,"lastUpdated":1745597424195}}},"paladin":{"paladin":{"internalLink":{"count":1,"lastUpdated":1745333066664}}},"Froggo":{"Froggo":{"internalLink":{"count":1,"lastUpdated":1745596559917}}},"The Fiend":{"warlock-the-fiend":{"internalLink":{"count":1,"lastUpdated":1745597052258}}},"two-weapon-fighting":{"two-weapon-fighting":{"internalLink":{"count":1,"lastUpdated":1745597177852}}},"Meows Whiskerpop (Whisky)":{"Meows Whiskerpop (Whisky)":{"internalLink":{"count":1,"lastUpdated":1745600510722}}},"05-personality-and-background":{"05-personality-and-background":{"internalLink":{"count":1,"lastUpdated":1745901627632}}},"dretch":{"dretch":{"internalLink":{"count":1,"lastUpdated":1746005076723}}},"imp":{"imp":{"internalLink":{"count":1,"lastUpdated":1746005636725}}}}