{"Link to me":{"Link to me":{"internalLink":{"count":1,"lastUpdated":1742801253386}}},"Links":{"Links":{"currentFile":{"count":3,"lastUpdated":1742806067512}}},"Prologue":{"Prologue":{"currentFile":{"count":1,"lastUpdated":1742805488194}}},"Overv":{"Overv":{"currentFile":{"count":1,"lastUpdated":1742816021746}}},"Plane of Greed - Smaug's Challenge":{"Plane of Greed - Smaug's Challenge":{"internalLink":{"count":1,"lastUpdated":1742816260444}}},"Sunless World - The Hidden Truth":{"Sunless World - The Hidden Truth":{"internalLink":{"count":1,"lastUpdated":1742816270400}}},"Fallen Paladin’s Past - A Father’s Burden":{"Fallen Paladin’s Past - A Father’s Burden":{"internalLink":{"count":1,"lastUpdated":1742816274426}}},"Tech-Dominant Plane - A Fistful of Schemes":{"Tech-Dominant Plane - A Fistful of Schemes":{"internalLink":{"count":1,"lastUpdated":1742816277914}}},"War-Torn Plane - Stalemate of the Titans":{"War-Torn Plane - Stalemate of the Titans":{"internalLink":{"count":1,"lastUpdated":1742816280825}}}}